MANIFEST.in
README.md
setup.cfg
setup.py
eegevt/__init__.py
eegevt/eventfile.py
eegevt.egg-info/PKG-INFO
eegevt.egg-info/SOURCES.txt
eegevt.egg-info/dependency_links.txt
eegevt.egg-info/top_level.txt