Metadata-Version: 1.0
Name: eegevt
Version: 0.1.6
Summary: Module for working with various EEG event file formats
Home-page: https://github.com/gjcooper/eegevt
Author: Gavin Cooper
Author-email: gjcooper@gmail.com
License: GPL v2.0
Keywords: EEG,event
Platform: UNKNOWN
